viadot/__init__.py
viadot/config.py
viadot/exceptions.py
viadot/signals.py
viadot/utils.py
viadot/examples/__init__.py
viadot/examples/sap_rfc/Dockerfile
viadot/examples/sap_rfc/README.md
viadot/examples/sap_rfc/build.sh
viadot/examples/sap_rfc/docker-compose.yml
viadot/examples/sap_rfc/requirements.txt
viadot/orchestration/__init__.py
viadot/orchestration/prefect/__init__.py
viadot/orchestration/prefect/exceptions.py
viadot/orchestration/prefect/utils.py
viadot/orchestration/prefect/flows/__init__.py
viadot/orchestration/prefect/flows/azure_sql_to_adls.py
viadot/orchestration/prefect/flows/bigquery_to_adls.py
viadot/orchestration/prefect/flows/business_core_to_parquet.py
viadot/orchestration/prefect/flows/cloud_for_customers_to_adls.py
viadot/orchestration/prefect/flows/cloud_for_customers_to_databricks.py
viadot/orchestration/prefect/flows/customer_gauge_to_adls.py
viadot/orchestration/prefect/flows/duckdb_to_parquet.py
viadot/orchestration/prefect/flows/duckdb_to_sql_server.py
viadot/orchestration/prefect/flows/duckdb_transform.py
viadot/orchestration/prefect/flows/ecb_to_redshift_spectrum.py
viadot/orchestration/prefect/flows/entraid_to_redshift_spectrum.py
viadot/orchestration/prefect/flows/epicor_to_parquet.py
viadot/orchestration/prefect/flows/eurostat_to_adls.py
viadot/orchestration/prefect/flows/exchange_rates_to_adls.py
viadot/orchestration/prefect/flows/exchange_rates_to_databricks.py
viadot/orchestration/prefect/flows/exchange_rates_to_redshift_spectrum.py
viadot/orchestration/prefect/flows/genesys_to_adls.py
viadot/orchestration/prefect/flows/hubspot_to_adls.py
viadot/orchestration/prefect/flows/hubspot_to_redshift_spectrum.py
viadot/orchestration/prefect/flows/matomo_to_redshift_spectrum.py
viadot/orchestration/prefect/flows/mediatool_to_adls.py
viadot/orchestration/prefect/flows/mindful_to_adls.py
viadot/orchestration/prefect/flows/onestream_data_adapters_to_redshift_spectrum.py
viadot2-2.3.1.dist-info/METADATA
viadot2-2.3.1.dist-info/WHEEL
viadot2-2.3.1.dist-info/licenses/LICENSE
viadot2-2.3.1.dist-info/RECORD
